[
  {
    "accountId": "zhanhao668",
    "displayName": "占豪"
  },
  {
    "accountId": "Bai-Cao-Yuan",
    "displayName": "百草园书店"
  },
  {
    "accountId": "DJ00123987",
    "displayName": "洞见"
  },
  {
    "accountId": "duhaoshu",
    "displayName": "十点读书"
  },
  {
    "accountId": "bitsea",
    "displayName": "槽边往事"
  },
  {
    "accountId": "iiidaily",
    "displayName": "视觉志"
  },
  {
    "accountId": "douban",
    "displayName": "每日豆瓣"
  },
  {
    "accountId": "juecezazhi",
    "displayName": "决策杂志"
  },
  {
    "accountId": "yanshulou2019",
    "displayName": "燕梳楼"
  },
  {
    "accountId": "qnwzwx",
    "displayName": "青年文摘"
  },
  {
    "accountId": "new-weekly",
    "displayName": "新周刊"
  },
  {
    "accountId": "youshucc",
    "displayName": "有书"
  },
  {
    "accountId": "ss48hao",
    "displayName": "绳师48号"
  },
  {
    "accountId": "newnew_XH",
    "displayName": "背包老非"
  },
  {
    "accountId": "gh_dbeaf05dc192",
    "displayName": "心语备忘录"
  },
  {
    "accountId": "thefair2",
    "displayName": "新世相"
  },
  {
    "accountId": "yer808",
    "displayName": "一星期一本书"
  },
  {
    "accountId": "YJwujian",
    "displayName": "永劫无间"
  },
  {
    "accountId": "gh_6e1a50938aa7",
    "displayName": "拾光慢读社"
  },
  {
    "accountId": "hanfu577",
    "displayName": "汉服"
  },
  {
    "accountId": "wxyqg188",
    "displayName": "风暴追踪者"
  },
  {
    "accountId": "shicitiandi",
    "displayName": "诗词天地"
  },
  {
    "accountId": "weixizhibei",
    "displayName": "卫夕指北"
  },
  {
    "accountId": "America_hq",
    "displayName": "环球网文娱"
  },
  {
    "accountId": "meirirenwu",
    "displayName": "每日人物"
  },
  {
    "accountId": "readingclub_btfx",
    "displayName": "帆书樊登讲书"
  },
  {
    "accountId": "Mysterrry",
    "displayName": "第一心理"
  },
  {
    "accountId": "fengtang1971",
    "displayName": "冯唐"
  },
  {
    "accountId": "ikanlixiang",
    "displayName": "看理想"
  },
  {
    "accountId": "lishi139",
    "displayName": "历史讲解员王汉周"
  },
  {
    "accountId": "tiancantudou1",
    "displayName": "天蚕土豆"
  },
  {
    "accountId": "film-douban",
    "displayName": "豆瓣电影"
  },
  {
    "accountId": "qingdaodzw",
    "displayName": "大众网青岛"
  },
  {
    "accountId": "vistaweek",
    "displayName": "Vista看天下"
  },
  {
    "accountId": "zhangdiancheng71",
    "displayName": "张殿成"
  },
  {
    "accountId": "godmeghost",
    "displayName": "非人哉"
  },
  {
    "accountId": "qiuzhenhai2014",
    "displayName": "邱震海"
  },
  {
    "accountId": "duoduodai1982",
    "displayName": "多多黛"
  },
  {
    "accountId": "sdrenwu",
    "displayName": "十点人物志"
  },
  {
    "accountId": "RXYSGXPT",
    "displayName": "日行一善共修平台"
  },
  {
    "accountId": "wodqbs",
    "displayName": "记忆承载"
  },
  {
    "accountId": "lsqstyq2023",
    "displayName": "我是历史其实挺有趣"
  },
  {
    "accountId": "CCA198105",
    "displayName": "中国书法家协会"
  },
  {
    "accountId": "ZNL118",
    "displayName": "正能量"
  },
  {
    "accountId": "JYXZ89896",
    "displayName": "每晚一卷书"
  },
  {
    "accountId": "bmy1979",
    "displayName": "秦始皇帝陵博物院"
  },
  {
    "accountId": "pingyuangongzi",
    "displayName": "平原公子"
  },
  {
    "accountId": "bibizooo",
    "displayName": "bibi动物园"
  },
  {
    "accountId": "solovehistory",
    "displayName": "最爱历史"
  },
  {
    "accountId": "gxwh001",
    "displayName": "国学文化"
  },
  {
    "accountId": "newWhatYouNeed",
    "displayName": "我要WhatYouNeed"
  },
  {
    "accountId": "dushu369com",
    "displayName": "读书369"
  },
  {
    "accountId": "gh_139c40f8a7c6",
    "displayName": "波元霸"
  },
  {
    "accountId": "xhmrdxwx",
    "displayName": "新华每日电讯"
  },
  {
    "accountId": "thepoemforyou",
    "displayName": "为你读诗"
  },
  {
    "accountId": "tingshu369",
    "displayName": "听书369"
  },
  {
    "accountId": "New90hour",
    "displayName": "挪威TALK"
  },
  {
    "accountId": "renwumag1980",
    "displayName": "人物"
  },
  {
    "accountId": "duzheweixin",
    "displayName": "读者"
  },
  {
    "accountId": "Monarch_Service",
    "displayName": "君呼"
  },
  {
    "accountId": "Read-journey",
    "displayName": "读书与旅行"
  },
  {
    "accountId": "shidian3650",
    "displayName": "十点文摘"
  },
  {
    "accountId": "vip950",
    "displayName": "FM950广西音乐台"
  },
  {
    "accountId": "yaojindushu1156",
    "displayName": "姚瑾读书"
  },
  {
    "accountId": "gh_019785efd7f2",
    "displayName": "吴文杂谈"
  },
  {
    "accountId": "yunshi911",
    "displayName": "云石"
  },
  {
    "accountId": "gh_420228ecf64d",
    "displayName": "叶尖情感"
  },
  {
    "accountId": "dzwz999",
    "displayName": "读文摘精选"
  },
  {
    "accountId": "modernsky19971227",
    "displayName": "摩登天空"
  },
  {
    "accountId": "jingshuoriben",
    "displayName": "静说日本"
  },
  {
    "accountId": "xiaoxiaoxia-a",
    "displayName": "主题局"
  },
  {
    "accountId": "shuizuizhongguo1",
    "displayName": "誰最中國"
  },
  {
    "accountId": "gh_253d9aab155e",
    "displayName": "秋韵墨香"
  },
  {
    "accountId": "gh_5bf6d5f59895",
    "displayName": "孤独自学"
  },
  {
    "accountId": "Puer-RM",
    "displayName": "普洱融媒"
  },
  {
    "accountId": "YXJZXD100",
    "displayName": "围炉共读"
  },
  {
    "accountId": "hanzhou006",
    "displayName": "汉周读书"
  },
  {
    "accountId": "gh_23856c8e50b8",
    "displayName": "古韵风雅集"
  },
  {
    "accountId": "ibookreview",
    "displayName": "新京报书评周刊"
  },
  {
    "accountId": "BeGrowing2025",
    "displayName": "阿正在成长"
  },
  {
    "accountId": "dashuxiangtan",
    "displayName": "大树乡谈"
  },
  {
    "accountId": "camera-man-cn",
    "displayName": "摄像人网"
  },
  {
    "accountId": "gh_02ced274f781",
    "displayName": "国漫中"
  },
  {
    "accountId": "penetratingview",
    "displayName": "灼见"
  },
  {
    "accountId": "ncpa66550000",
    "displayName": "国家大剧院"
  },
  {
    "accountId": "shyufotemple_gf",
    "displayName": "上海玉佛禅寺"
  },
  {
    "accountId": "jiqunfashi",
    "displayName": "济群法师"
  },
  {
    "accountId": "hbsbwg",
    "displayName": "湖北省博物馆"
  },
  {
    "accountId": "dushu3690",
    "displayName": "名著听书"
  },
  {
    "accountId": "yujianxiaomi2015",
    "displayName": "遇见小mi"
  },
  {
    "accountId": "qingweiwenhuayishu",
    "displayName": "青未文化艺术"
  },
  {
    "accountId": "wallpaper_china",
    "displayName": "卷宗Wallpaper"
  },
  {
    "accountId": "BAZAARART2011",
    "displayName": "时尚芭莎艺术"
  },
  {
    "accountId": "boyin_China",
    "displayName": "播音中国"
  },
  {
    "accountId": "zhufu569",
    "displayName": "传统节日祝福"
  },
  {
    "accountId": "gh_efb438315974",
    "displayName": "羽羽羽表情包"
  },
  {
    "accountId": "nulishehui",
    "displayName": "奴隶社会"
  },
  {
    "accountId": "renwen-zhichuang",
    "displayName": "人文之窗"
  },
  {
    "accountId": "zhiliangzhiSHY",
    "displayName": "北京知行合一阳明教育研究院"
  },
  {
    "accountId": "sdck789",
    "displayName": "深度参考"
  }
]